setup.py
ao_aws_ml_course/Binomialdistribution.py
ao_aws_ml_course/Gaussiandistribution.py
ao_aws_ml_course/Generaldistribution.py
ao_aws_ml_course/__init__.py
ao_aws_ml_course.egg-info/PKG-INFO
ao_aws_ml_course.egg-info/SOURCES.txt
ao_aws_ml_course.egg-info/dependency_links.txt
ao_aws_ml_course.egg-info/not-zip-safe
ao_aws_ml_course.egg-info/top_level.txt